odoo9_addon_web_widget_many2many_tags_multi_selection-9.0.1.1.0-py2.7-nspkg.pth
odoo_addons/web_widget_many2many_tags_multi_selection/__openerp__.py
odoo_addons/web_widget_many2many_tags_multi_selection/__init__.py
odoo_addons/web_widget_many2many_tags_multi_selection/README.rst
odoo_addons/web_widget_many2many_tags_multi_selection/views/web_widget_many2many_tags_multi_selection.xml
odoo_addons/web_widget_many2many_tags_multi_selection/static/description/icon.png
odoo_addons/web_widget_many2many_tags_multi_selection/static/src/js/view_form.js
odoo9_addon_web_widget_many2many_tags_multi_selection-9.0.1.1.0.dist-info/top_level.txt
odoo9_addon_web_widget_many2many_tags_multi_selection-9.0.1.1.0.dist-info/WHEEL
odoo9_addon_web_widget_many2many_tags_multi_selection-9.0.1.1.0.dist-info/RECORD
odoo9_addon_web_widget_many2many_tags_multi_selection-9.0.1.1.0.dist-info/metadata.json
odoo9_addon_web_widget_many2many_tags_multi_selection-9.0.1.1.0.dist-info/DESCRIPTION.rst
odoo9_addon_web_widget_many2many_tags_multi_selection-9.0.1.1.0.dist-info/METADATA
odoo9_addon_web_widget_many2many_tags_multi_selection-9.0.1.1.0.dist-info/namespace_packages.txt
