Metadata-Version: 2.0
Name: odoo9-addon-web-widget-many2many-tags-multi-selection
Version: 9.0.1.1.0
Summary: Tags multiple selection
Home-page: https://www.akretion.com
Author: UNKNOWN
Author-email: UNKNOWN
License: UNKNOWN
Platform: UNKNOWN
Requires-Dist: odoo (<9.1a,>=9.0a)
Classifier: Programming Language :: Python :: 2.7
Classifier: Framework :: Odoo
